{
  "users": [],
  "display_name": "Open Data Ireland",
  "description": "We are exploring the use of this Data Hub group as a replacement for the [Irish Open Data community catalog](http://ie.ckan.net/). Stay tuned…",
  "created": "2011-10-28T16:54:59.650851",
  "package_count": 0,
  "title": "Open Data Ireland",
  "name": "ireland",
  "is_organization": true,
  "state": "active",
  "extras": [],
  "groups": [],
  "type": "organization",
  "revision_id": "ebc14db2-f7a0-4a30-a7dd-aa3048ac7948",
  "num_followers": 0,
  "id": "c3a7f769-6fd6-48ea-8d3a-858d4d3869dd",
  "tags": [],
  "approval_status": "approved"
}