{
  "license_title": "",
  "maintainer": "",
  "relationships_as_object": [],
  "private": false,
  "maintainer_email": "",
  "num_tags": 0,
  "id": "c0a012c7-2189-4413-925f-f81e74d1644a",
  "metadata_created": "2012-06-04T17:43:50.852277",
  "metadata_modified": "2013-10-10T20:49:37.264020",
  "author": "",
  "author_email": "",
  "state": "active",
  "version": "",
  "creator_user_id": "6f604955-8cdd-4201-b7f1-1a009bef3d00",
  "type": "dataset",
  "resources": [
    {
      "mimetype": "application/octet-stream",
      "cache_url": "",
      "hash": "5a76b3ae5e664f4f30584b758826843f04ffdd23",
      "description": "The one master document that contains the key information for all e-petitions on the site.",
      "name": "petitions.json",
      "format": "JSON",
      "url": "http://epetitions.direct.gov.uk/api/petitions.json",
      "datastore_active": false,
      "cache_last_updated": null,
      "package_id": "c0a012c7-2189-4413-925f-f81e74d1644a",
      "created": "2012-06-04T17:43:50.941142",
      "state": "active",
      "mimetype_inner": "",
      "last_modified": "2012-06-04T17:45:56.231094",
      "position": 0,
      "revision_id": "f6a05110-e0f5-4eaf-97c2-5edfe6a046c5",
      "url_type": null,
      "id": "b751c531-c1c7-49a1-9e5d-68c0389cf3f2",
      "resource_type": "file",
      "size": "22370833"
    }
  ],
  "num_resources": 1,
  "tags": [],
  "groups": [],
  "license_id": "",
  "relationships_as_subject": [],
  "organization": {
    "description": "",
    "created": "2013-10-10T14:24:46.556146",
    "title": "Global",
    "name": "global",
    "is_organization": true,
    "state": "active",
    "image_url": "",
    "revision_id": "6f9b4b38-6781-489c-bb4d-ea106ee7ac37",
    "type": "organization",
    "id": "94d03217-717d-41ce-a20c-00e754e94183",
    "approval_status": "approved"
  },
  "name": "epetitions-direct-gov-uk",
  "isopen": false,
  "url": "http://epetitions.direct.gov.uk",
  "notes": "UK government e-petitions website.",
  "owner_org": "94d03217-717d-41ce-a20c-00e754e94183",
  "extras": [],
  "title": "epetitions.direct.gov.uk",
  "revision_id": "3762bc37-d99a-4204-8f01-2eaa5ae1a56b"
}