{
  "license_title": "License not specified",
  "maintainer": "",
  "relationships_as_object": [],
  "private": false,
  "maintainer_email": "",
  "num_tags": 4,
  "id": "231eed17-e4f2-46ac-a02c-4c94a32c3362",
  "metadata_created": "2010-12-20T19:43:58.647747",
  "metadata_modified": "2013-10-10T20:32:42.449999",
  "author": "Pippa Norris",
  "author_email": "Pippa_Norris@Harvard.edu",
  "state": "active",
  "version": "January 2009",
  "creator_user_id": "76ad6278-be3c-4307-8b42-3b214d6c063c",
  "type": "dataset",
  "resources": [
    {
      "mimetype": "",
      "cache_url": null,
      "hash": "",
      "description": "CSV Data File",
      "format": "CSV",
      "url": "http://www.hks.harvard.edu/fs/pnorris/Data/Democracy%20CrossNational%20Data/Democracy%20Crossnational%20Data%20Spring%202009.csv",
      "datastore_active": false,
      "cache_last_updated": null,
      "package_id": "231eed17-e4f2-46ac-a02c-4c94a32c3362",
      "name": "",
      "state": "active",
      "mimetype_inner": "",
      "last_modified": null,
      "position": 0,
      "revision_id": "b3212836-dbbc-47e5-b9ba-b4c4b1b3e6b7",
      "url_type": null,
      "id": "bfb4da1d-46e2-40af-945e-0b64813458f2",
      "resource_type": "file",
      "size": null
    },
    {
      "mimetype": "",
      "cache_url": null,
      "hash": "",
      "description": "Excel Data File",
      "format": "XLS",
      "url": "http://www.hks.harvard.edu/fs/pnorris/Data/Democracy%20CrossNational%20Data/Democracy%20Crossnational%20Data%20Spring%202009%20Excel.xlsx",
      "datastore_active": false,
      "cache_last_updated": null,
      "package_id": "231eed17-e4f2-46ac-a02c-4c94a32c3362",
      "name": "",
      "state": "active",
      "mimetype_inner": "",
      "last_modified": null,
      "position": 1,
      "revision_id": "b3212836-dbbc-47e5-b9ba-b4c4b1b3e6b7",
      "url_type": null,
      "id": "d7213208-75e8-4d25-be23-bb85728931e7",
      "resource_type": "file",
      "size": null
    },
    {
      "mimetype": "",
      "cache_url": null,
      "hash": "",
      "description": "SPSS Data File",
      "format": "SPSS",
      "url": "http://www.hks.harvard.edu/fs/pnorris/Data/Democracy%20CrossNational%20Data/Democracy%20Crossnational%20Data%20Spring%202009.sav",
      "datastore_active": false,
      "cache_last_updated": null,
      "package_id": "231eed17-e4f2-46ac-a02c-4c94a32c3362",
      "name": "",
      "state": "active",
      "mimetype_inner": "",
      "last_modified": null,
      "position": 2,
      "revision_id": "b3212836-dbbc-47e5-b9ba-b4c4b1b3e6b7",
      "url_type": null,
      "id": "c735062f-a2a1-47ab-9466-8060d9f2354a",
      "resource_type": "file",
      "size": null
    },
    {
      "mimetype": "",
      "cache_url": null,
      "hash": "",
      "description": "Stata Data File",
      "format": "Stata",
      "url": "http://www.hks.harvard.edu/fs/pnorris/Data/Democracy%20CrossNational%20Data/Democracy%20Crossnational%20Data%20Spring%202009%20StataSE.dta",
      "datastore_active": false,
      "cache_last_updated": null,
      "package_id": "231eed17-e4f2-46ac-a02c-4c94a32c3362",
      "name": "",
      "state": "active",
      "mimetype_inner": "",
      "last_modified": null,
      "position": 3,
      "revision_id": "b3212836-dbbc-47e5-b9ba-b4c4b1b3e6b7",
      "url_type": null,
      "id": "75ec6b75-5620-48a3-9b8a-58b9d222fc14",
      "resource_type": "file",
      "size": null
    }
  ],
  "num_resources": 4,
  "tags": [
    {
      "vocabulary_id": null,
      "state": "active",
      "display_name": "democracy",
      "id": "9f3bcf5c-59e3-412c-8c9a-d1ea4655d6d5",
      "name": "democracy"
    },
    {
      "vocabulary_id": null,
      "state": "active",
      "display_name": "growth",
      "id": "6652f598-cd04-4150-ac8a-790264c382ee",
      "name": "growth"
    },
    {
      "vocabulary_id": null,
      "state": "active",
      "display_name": "institutions",
      "id": "ab87629a-338b-48d5-b7b7-ea4a9d5b2032",
      "name": "institutions"
    },
    {
      "vocabulary_id": null,
      "state": "active",
      "display_name": "regression",
      "id": "b4594b74-7e5a-4e78-a433-ee61ca309e5b",
      "name": "regression"
    }
  ],
  "groups": [],
  "license_id": "notspecified",
  "relationships_as_subject": [],
  "organization": {
    "description": "",
    "created": "2013-10-10T14:24:46.556146",
    "title": "Global",
    "name": "global",
    "is_organization": true,
    "state": "active",
    "image_url": "",
    "revision_id": "6f9b4b38-6781-489c-bb4d-ea106ee7ac37",
    "type": "organization",
    "id": "94d03217-717d-41ce-a20c-00e754e94183",
    "approval_status": "approved"
  },
  "name": "democracy-time-series-dataset---variable-labels",
  "isopen": false,
  "url": "http://www.hks.harvard.edu/fs/pnorris/Data/Data.htm",
  "notes": "Democracy Timeseries Data Release 3.0, January 2009\r\n\r\nThis dataset is in a country-year case format, suitable for time-series analysis. It contains data on the social, economic and political characteristics of 191 nations with over 600 variables from 1971 to 2007.  It merges the indicators of democracy by Freedom House, Vanhanen, Polity IV, and Cheibub and Gandhi, plus selected institutional classifications and also socio-economic indicators from the World Bank. New variables including the KOF Globalization Index and the new Norris-Inglehart Cosmopolitan Index.  Note that you should check the original codebooks for the meaning and definition of each of the variables. The period for each series also varies. Note that the Excel version is for Office 2007 only. This is the dataset used in the book, Driving Democracy.\r\n\r\nJanuary 2009\r\n\r\nStored in Stata, SPSS, Excel and CSV.",
  "owner_org": "94d03217-717d-41ce-a20c-00e754e94183",
  "extras": [],
  "title": "Democracy time-series dataset: Variable labels.",
  "revision_id": "c5cf9508-319d-4169-91db-ae1168ca012a"
}