{
  "license_title": "",
  "maintainer": "",
  "relationships_as_object": [],
  "private": false,
  "maintainer_email": "",
  "num_tags": 5,
  "id": "be3a08d2-e745-4ab7-b40d-474013a3ec11",
  "metadata_created": "2013-03-29T10:15:34.873986",
  "metadata_modified": "2013-10-10T23:25:46.702940",
  "author": "",
  "author_email": "",
  "state": "active",
  "version": "",
  "creator_user_id": "f2aad7a3-0ad2-4ef9-8931-0277987525e9",
  "type": "dataset",
  "resources": [
    {
      "mimetype": "application/pdf",
      "cache_url": "",
      "hash": "",
      "description": "",
      "name": "",
      "format": "",
      "url": "http://www.ansd.sn/publications/conjoncturelles/ReperStat/ReperStat_09_11.pdf",
      "datastore_active": false,
      "cache_last_updated": null,
      "package_id": "be3a08d2-e745-4ab7-b40d-474013a3ec11",
      "created": "2013-03-29T05:15:35.233301",
      "state": "active",
      "mimetype_inner": "",
      "last_modified": "2013-03-29T05:15:36.374290",
      "position": 0,
      "revision_id": "e52228f9-e573-4ace-879a-21d044d64cb9",
      "url_type": null,
      "id": "9a1ea1d7-5a75-4335-b2b2-58658cf17438",
      "resource_type": "",
      "size": "201991"
    }
  ],
  "num_resources": 1,
  "tags": [
    {
      "vocabulary_id": null,
      "state": "active",
      "display_name": "ANSD",
      "id": "3aebb1ae-0688-442f-bca7-7344eba96c6b",
      "name": "ANSD"
    },
    {
      "vocabulary_id": null,
      "state": "active",
      "display_name": "Senegal",
      "id": "01eda3fc-b8f4-4f71-bd78-2c4efeddfa96",
      "name": "Senegal"
    },
    {
      "vocabulary_id": null,
      "state": "active",
      "display_name": "donnees",
      "id": "6fb26362-d567-4bae-be5a-55553ecc6f0c",
      "name": "donnees"
    },
    {
      "vocabulary_id": null,
      "state": "active",
      "display_name": "menages",
      "id": "dd524ba9-352c-4a11-a567-a1a8ed6940fc",
      "name": "menages"
    },
    {
      "vocabulary_id": null,
      "state": "active",
      "display_name": "publications",
      "id": "c93ebe8f-83a0-498c-8704-1de94db149e9",
      "name": "publications"
    }
  ],
  "groups": [],
  "license_id": "",
  "relationships_as_subject": [],
  "organization": {
    "description": "Datasets for Senegal, which launched in  Mars 2013, is a Senegal, citizen-led effort to promote open data and help share data that has already been liberated.\r\nhttp://senegalouvert.org",
    "created": "2013-03-06T08:41:09.889284",
    "title": "Senegal",
    "name": "country-sn",
    "is_organization": true,
    "state": "active",
    "image_url": "http://upload.wikimedia.org/wikipedia/commons/archive/f/fd/20060623150931%21Flag_of_Senegal.svg",
    "revision_id": "864359e1-276d-4f94-8b6a-86e660e14929",
    "type": "organization",
    "id": "99975e34-178e-4edc-974d-8c0ec2fd98b3",
    "approval_status": "approved"
  },
  "name": "rep-re-statistiques-septembre-2011",
  "isopen": false,
  "url": "http://www.ansd.sn/publications/conjoncturelles/ReperStat/ReperStat_09_11.pdf",
  "notes": "REPUBLIQUE DU SENEGAL Un Peuple  Un But  Une Foi  MINISTERE DE LECONOMIE  ET DES FINANCES                                                            Rue de Diourbel X rue de SaintLouis  Point E  BP 116 Dakar RP  Tel : 33 869 21 46 / 33  869 21 39    Fax : 33 869 21 63    Site Web: www ansdsn \fI  CONTEXTE INTERNATIONAL  11  Poursuite  de  la  progression  des  cours  du  riz  (+8,1%),  légère  reprise  des  cours  moyens  du  baril  du pétrole  brut  (+0,6%)  et  hausse  des  cours moyens  du  coton  (+3,1%)  Le  sucre  (4,2%),  le  blé  (5,4%)  et  le maïs (3,4%) ont chuté en septembre 2011 Unité sept10 juin11 juil11 août11 sept11 moyenne 9 mois Variation(en %) 2010 2011 sept11/ août11 sept11/ sept10 9 mois11/ 9 mois10 US $/baril US $/tonne US cents / bois de 60lb US cents / boisseau New york  cents/lb n°11 US cents/lb 77,8 483,0 113,9 515,7 116,5517,3704,6 695,8 668,7482,8 720,7 683,723,7 104,7 26,1 121,7 29,5121,7110,1564,6717,4713,428,9113,6110,8610,577,1483,0679,0704,6689,2482,827,7117,123,7104,7111,6 552,0 690,2 701,8 28,1 118,5 0,6 8,1 5,4 3,4 4,2 3,1 42,426,43,642,816,911,844,714,32,045,418,413,2Evolution du cours moyen mensuel du baril de pétrole brut (en dollar US)Matières premières Pétrole brut riz Blé Maïs Sucre Coton Source : INSEE  150135120105907560453080vnaj80sram80iam80liuj80tpes80von90vnaj90sram90iam90liuj90tpes90von01vnaj01sram01iam01liuj01tpes01von11vnaj11sram11iam11liuj11tpes   Source : INSEE 21   Poursuite de la baisse de lactivité économique, hors agriculture, au mois de septembre 2011 Indice Général dActivité par secteurs (base 100 en 2006) II ACTIVITE ECONOMIQUE SECTEURS Pond sept10 juin11 juil11 août11 sept11  variation (en %) sept11/ août11 sept11/ sept10 PRIMAIRE (hors Agriculture) SECONDAIRE TERTIAIRE (hors administration) ADMINISTRATION PUBLIQUE TAXE SUR BIEN ET SERVICES 5,9 21,9 53,5 6 13,4 110,298,3119,5107,8102,1115,1131,2131110,4110,7117,3136,6132,3113121,7109,1127,4133,8113,1110,9102,3 122,9 125,8 113,7 103,5 6,23,56,00,66,77,225,05,25,61,4INDICE D'ENSEMBLE Source : DPEE 22  Hausse  de  la  production  de  phosphates  (+19,0%)  et  dattapulgite  (+48,5%)  Par  contre,  la  production de  phosphates  de  chaux  et  de  sel  marin  iodé  ont  respectivement  chuté  de  (75,0%)  et  (27,4%)  en septembre 2011 120,2 111,4100 126,3129,9126,85,27,9Principales productions minières Produits Unités sept10 juin11 juil11 août11 sept11 moyenne des 9 mois 2010 2011 Milliers Tonnes  Phosphates Attapulgite Milliers Tonnes  Sel marin iode  Milliers Tonnes  Calcaire Basalte Phosphates de chaux Milliers M3 Milliers M3 Milliers Tonnes  Source : ANSD  52 8,8 19,7 47 55,7 0,1 122 11,7 24,3 51,7 64,1 2,9 711523,974,967,45,21059,725,9ndnd2,412514,418,8ndnd0,684,2 15,2 18,6 1,4 Variation(en %) sept11/ août11 19,0 48,5 27,4   sept11/ sept10 140,463,64,69 mois11/ 9 mois10 32,54,514,4111,6  14,5  21,3    2,4  75,0 500,071,4 1\f",
  "owner_org": "99975e34-178e-4edc-974d-8c0ec2fd98b3",
  "extras": [],
  "title": "Repère Statistiques Septembre 2011",
  "revision_id": "659f7946-09ad-4532-bcba-b24d9dca23d8"
}