{
  "license_title": "Creative Commons Attribution Share-Alike",
  "maintainer": null,
  "relationships_as_object": [],
  "private": false,
  "maintainer_email": "lod-it@netseven.it",
  "num_tags": 5,
  "id": "765a9a33-01b0-473b-9c8e-c20f74227cd7",
  "metadata_created": "2014-11-27T20:13:34.344421",
  "metadata_modified": "2014-11-27T20:13:34.344421",
  "author": "Linkedopendata.it",
  "author_email": "lod@netseven.it",
  "state": "active",
  "version": "1.0",
  "creator_user_id": "db0c8e88-09a8-4f8a-adf6-dca697138f22",
  "type": "dataset",
  "resources": [
    {
      "mimetype": null,
      "cache_url": null,
      "hash": "",
      "description": "Grafo RDF",
      "name": null,
      "format": "RDF",
      "url": "http://dump.linkedopendata.it/musei",
      "datastore_active": false,
      "cache_last_updated": null,
      "package_id": "765a9a33-01b0-473b-9c8e-c20f74227cd7",
      "created": "2014-11-27T20:13:34.850550",
      "state": "active",
      "mimetype_inner": null,
      "last_modified": null,
      "position": 0,
      "revision_id": "15276043-ac11-4fb4-aaf0-76eda7ba18dc",
      "url_type": null,
      "id": "ee68577d-237c-4bc6-964c-f5a39b392f37",
      "resource_type": null,
      "size": null
    },
    {
      "mimetype": null,
      "cache_url": null,
      "hash": "",
      "description": "SPARQL endpoint",
      "name": null,
      "format": "SPARQL endpoint",
      "url": "http://sparql.linkedopendata.it/musei",
      "datastore_active": false,
      "cache_last_updated": null,
      "package_id": "765a9a33-01b0-473b-9c8e-c20f74227cd7",
      "created": "2014-11-27T20:13:34.850655",
      "state": "active",
      "mimetype_inner": null,
      "last_modified": null,
      "position": 1,
      "revision_id": "15276043-ac11-4fb4-aaf0-76eda7ba18dc",
      "url_type": null,
      "id": "84754135-fb81-4013-a80d-2fa798c332fb",
      "resource_type": null,
      "size": null
    }
  ],
  "num_resources": 2,
  "tags": [
    {
      "vocabulary_id": null,
      "state": "active",
      "display_name": "italia",
      "id": "8aa8e42d-3758-41f5-a805-628619f4e26e",
      "name": "italia"
    },
    {
      "vocabulary_id": null,
      "state": "active",
      "display_name": "linkeddata",
      "id": "7b2b43f4-096d-4367-b702-e1d1a8442664",
      "name": "linkeddata"
    },
    {
      "vocabulary_id": null,
      "state": "active",
      "display_name": "lod",
      "id": "54a512d9-f003-4b79-badf-c85bfa977a7e",
      "name": "lod"
    },
    {
      "vocabulary_id": null,
      "state": "active",
      "display_name": "meta.imported-from.it.ckan.net",
      "id": "88cba689-c1ae-45e9-8a3f-094a970a0e90",
      "name": "meta.imported-from.it.ckan.net"
    },
    {
      "vocabulary_id": null,
      "state": "active",
      "display_name": "musei",
      "id": "3e5507be-c7b7-4f56-a9d6-733ea99c85bb",
      "name": "musei"
    }
  ],
  "groups": [],
  "license_id": "cc-by-sa",
  "relationships_as_subject": [],
  "organization": {
    "description": "",
    "created": "2014-11-27T20:09:07.202281",
    "title": "it-ckan-net",
    "name": "it-ckan-net",
    "is_organization": true,
    "state": "active",
    "image_url": "",
    "revision_id": "0ec99197-36a7-4b4d-96be-74b614af4b67",
    "type": "organization",
    "id": "15e24750-6eb6-4495-99bd-6c211ea1a0e2",
    "approval_status": "approved"
  },
  "name": "musei-italiani",
  "isopen": true,
  "url": "http://www.linkedopendata.it/datasets/musei",
  "notes": "Questo dataset contiene una lista geo-referenziata dei musei italiani divisi in categorie. Le categorie sono identificate da risorse descritte in DBPedia.\r\n\r\nLe località menzionate nel dataset sono, ove possibile, collegate alle rispettive risorse in Geonames.",
  "owner_org": "15e24750-6eb6-4495-99bd-6c211ea1a0e2",
  "extras": [],
  "license_url": "http://www.opendefinition.org/licenses/cc-by-sa",
  "title": "Musei Italiani",
  "revision_id": "15276043-ac11-4fb4-aaf0-76eda7ba18dc"
}